bgraph/__init__.py
bgraph/__main__.py
bgraph/builder/__init__.py
bgraph/builder/builder.py
bgraph/builder/graph.py
bgraph/exc.py
bgraph/main.py
bgraph/parsers/__init__.py
bgraph/parsers/soong_parser.py
bgraph/types.py
bgraph/utils.py
bgraph/viewer/__init__.py
bgraph/viewer/formatter.py
bgraph/viewer/loader.py
bgraph/viewer/viewer.py
bgraph-0.1.0.dist-info/entry_points.txt
bgraph-0.1.0.dist-info/LICENSE.md
bgraph-0.1.0.dist-info/WHEEL
bgraph-0.1.0.dist-info/METADATA
bgraph-0.1.0.dist-info/RECORD
