Metadata-Version: 2.1
Name: bgraph
Version: 0.1.0
Summary: 
License: Apache-2.0
Author: A. Challande
Author-email: achallande@quarkslab.com
Requires-Python: >=3.8,<4.0
Classifier: License :: OSI Approved :: Apache Software License
Classifier: Operating System :: Android
Classifier: Programming Language :: Python :: 3
Classifier: Programming Language :: Python :: 3.8
Classifier: Programming Language :: Python :: 3.9
Classifier: Topic :: Security
Classifier: Topic :: Software Development :: Build Tools
Provides-Extra: doc
Requires-Dist: mkdocs (>=1.1.2,<2.0.0); extra == "doc"
Requires-Dist: mkdocs-material (>=7.1.3,<8.0.0); extra == "doc"
Requires-Dist: mkdocstrings (>=0.15.0,<0.16.0); extra == "doc"
Requires-Dist: networkx (>=2.5,<3.0)
Requires-Dist: pydot (>=1.4.2,<2.0.0)
Requires-Dist: pyparsing (>=2.4.7,<3.0.0)
Requires-Dist: rich (>=9.11.0,<10.0.0)
Requires-Dist: sh (>=1.14.1,<2.0.0)
Requires-Dist: typer[all] (>=0.3.2,<0.4.0)
Requires-Dist: untangle (>=1.1.1,<2.0.0)
Project-URL: Documentation, https://achallande.doc.qb/bgraph/
